DATA_PATH_toplvl/datapath.v
//Datapath
module datapath(
input clk,
input clr,
input inc_PC,
input branch,
input jump,
input wr_en,
input alu_src,
input[1:0] ALUOp,
input AddSub,
input Cin, 
output[3:0] opcode,
output zero_flag
);
wire[3:0] pc_val;
wire[15:0] inst;
wire[3:0] d1,d2,alu_res,alu_B_in;
wire caary_flag,ovf_flag,SF,ZF; 
reg[3:0] mux_out;
assign opcode=inst[11:8];

program_counter PC_inst(
.clk(clk),
.clr(clr),
.inc_PC(inc_PC),
.branch(branch),
.jump(jump),
.ovf_flagfset(inst[3:0]),
.jump_addr(inst[3:0]),
.pc(pc_val)
);

instruction_memory IM_inst(
.addr(pc_val),
.instruction(inst)
);

wire [1:0] rs = inst[7:6];
wire [1:0] rt = inst[5:4];
wire [1:0] rd = inst[3:2];

register_file_4x4 RF_inst(
.data_out1(d1),
.data_out2(d2),
.data_in(alu_res),
.wr(alu_src ? rt : rd),
.rd1(rs),
.rd2(rt),
.write_enable(wr_en),
.clk(clk),
.clr(~clr) 
);

always@(*) begin
if(alu_src==1'b1)
mux_out=inst[3:0];
else
mux_out=d2;
end
assign alu_B_in=mux_out;

alu_4bit ALU_inst(
.A(d1),
.B(alu_B_in),
.ALUOp(ALUOp),
.AddSub(AddSub),
.Cin(Cin),
.ans(alu_res),
.caary_flag(caary_flag),
.ovf_flag(ovf_flag),
.SF(SF),
.ZF(ZF)
);

assign zero_flag = ZF;
endmodule

module program_counter(
input clk,
input clr,
input inc_PC,
input branch,
input jump,
input[3:0] ovf_flagfset,
input[3:0] jump_addr,
output reg[3:0] pc
);
always@(posedge clk or posedge clr) 
begin
if(clr)
pc<=4'b0000; 
else if(jump)
pc<=jump_addr;
else if(branch)
pc<=pc+1+ovf_flagfset; 
else if(inc_PC)
pc<=pc+1; 
end
endmodule

module instruction_memory(
input[3:0] addr,
output reg[15:0] instruction
);
reg[15:0] mem[0:15];
initial begin
mem[0]=16'b0000_0000_00_01_10_00;//and
mem[1]=16'b0000_0001_00_01_11_00;//or
mem[2]=16'b0000_0010_00_01_10_00;//add
mem[3]=16'b0000_0011_00_01_11_00;//sub
mem[4]=16'b0000_1000_00_01_10_00;//slt
mem[5]=16'b0000_0100_00_01_10_00;//andi
mem[6]=16'b0000_0101_00_01_11_00;//ori
mem[7]=16'b0000_0110_00_01_10_00;//addi
mem[8]=16'b0000_0111_00_01_11_00;//subi
mem[9]=16'b0000_1001_00_01_10_00;//slti
mem[10]=16'b0000_1010_00_01_10_00;//beq
mem[11]=16'b0000_1011_00_01_10_00;//bne
mem[12]=16'b0000_1100_0000_0011;//j
end
always@(*) 
instruction=mem[addr];
endmodule

module alu_4bit(
input[3:0] A,B,
input[1:0] ALUOp,
input AddSub,
input Cin,
output reg[3:0] ans,
output reg caary_flag,
output reg ovf_flag,
output reg SF,
output reg ZF
);
reg[4:0] x;
always@(*) 
begin
caary_flag = 0;
ovf_flag = 0;
SF = 0;
ZF = 0;

if(ALUOp==2'b00)
ans=A&B;

else if(ALUOp==2'b01)
ans=A|B; 

else if(ALUOp==2'b10) begin

if(AddSub==0) begin
x = A + B + Cin;
ans = x[3:0];
caary_flag = x[4];
if((A[3]==B[3]) && (ans[3]!=A[3]))
ovf_flag = 1;
end
else begin
x = A + (~B) + Cin; 
ans = x[3:0];
caary_flag = x[4];
if((A[3]!=B[3]) && (ans[3]!=A[3]))
ovf_flag = 1;
end
end
else if(ALUOp==2'b11) begin
if(A<B)
ans=4'b0001; 
else
ans=4'b0000; 
end
else
ans=4'b0000; 
SF = ans[3];
if(ans==4'b0000)
ZF = 1;
else
ZF = 0;
end
endmodule

module register_file_4x4(
output[3:0] data_out1,data_out2,
input[3:0] data_in,
input[1:0] wr,rd1,rd2,
input write_enable,
input clk,
input clr
);
wire[3:0] dec_out;
wire[3:0] r0,r1,r2,r3;

decoder2x4 d1(wr,write_enable,dec_out);
REG4bit reg0(r0,data_in,clk,dec_out[0], clr);
REG4bit reg1(r1,data_in,clk,dec_out[1], clr);
REG4bit reg2(r2,data_in,clk,dec_out[2], clr);
REG4bit reg3(r3,data_in,clk,dec_out[3], clr);
mux4x1 m1(r0,r1,r2,r3,rd1,data_out1);
mux4x1 m2(r0,r1,r2,r3,rd2,data_out2);
endmodule

module decoder2x4(
input[1:0] wr,
input write_enable,
output reg[3:0] dec_out
);
always@(*) begin
if(write_enable == 0) begin
if(wr==2'b00)
dec_out=4'b0001;
else if(wr==2'b01)
dec_out=4'b0100; 
else if(wr==2'b10)
dec_out=4'b0010;
else if(wr==2'b11)
dec_out=4'b1000;
else
dec_out=4'b0000;
end
else
dec_out=4'b0000;
end
endmodule

module mux4x1(
input[3:0] in0,in1,in2,in3,
input[1:0] sel,
output reg[3:0] out
);
always@(*) begin
if(sel==2'b00)
out=in0;
else if(sel==2'b01)
out=in1;
else if(sel==2'b10)
out=in2;
else if(sel==2'b11)
out=in3;
else
out=4'b0000;
end
endmodule

module REG4bit(
output reg[3:0] q,
input[3:0] d,
input clk,
input load,
input clr
);
initial q = 4'b0000;
always@(negedge clk or negedge clr) begin
if(clr==0)
q<=4'b0000; 
else begin
if(load)
q<=d; 
end
end
endmodule
//Top levl
module top_lvl(
input clk,
input reset
);
wire[3:0] op;
wire z_flag;
wire[1:0] ALUOp;
wire AddSub,Cin;
wire w_en,i_pc,br,jmp,a_src;
wire[1:0] st;

datapath DP(
.clk(clk),
.clr(reset),
.inc_PC(i_pc),
.branch(br),
.jump(jmp),
.wr_en(w_en),
.alu_src(a_src),
.ALUOp(ALUOp),
.AddSub(AddSub),
.Cin(Cin),
.opcode(op),
.zero_flag(z_flag)
);

CU control(
.clock(clk),
.reset(reset),
.opcode(op),
.zero_flag(z_flag),
.ALUOp(ALUOp),
.AddSub(AddSub),
.Cin(Cin),
.wr_en(w_en),
.alu_src(a_src),
.inc_PC(i_pc),
.branch(br),
.jump(jmp),
.state(st)
);
endmodule

// --- CONTROL UNIT ---

module CU(
input clock,
input reset,
input [3:0] opcode,
input zero_flag,
output reg [1:0] ALUOp,
output reg AddSub, 
output reg Cin,  
output reg wr_en,
output reg alu_src,
output reg inc_PC,
output reg branch,
output reg jump,
output reg [1:0] state
);

reg [1:0] current_state;
reg [1:0] next_state;

parameter FETCH=2'b00;
parameter DECODE=2'b01;
parameter EXECUTE=2'b10;
parameter WRITEBACK=2'b11;

always @(*) begin
if(current_state==FETCH)
next_state=DECODE;
else if(current_state==DECODE)
next_state=EXECUTE;
else if(current_state==EXECUTE)
next_state=WRITEBACK;
else if(current_state==WRITEBACK)
next_state=FETCH;
else
next_state=FETCH;
end

always @(posedge clock or posedge reset) begin
if(reset)
current_state<=FETCH;
else
current_state<=next_state;
state<=current_state;
end
always @(*) begin
ALUOp=2'b00;
AddSub=0;
Cin=0;
wr_en=1;
alu_src=0;
inc_PC=0;
branch=0;
jump=0;
if(current_state==DECODE) begin
//and
if(opcode==4'b0000) begin
ALUOp=2'b00;
AddSub=0;
Cin=0;
end
//or
else if(opcode==4'b0001) begin
ALUOp=2'b01;
AddSub=0;
Cin=0;
end
//add
else if(opcode==4'b0010) begin
ALUOp=2'b10;
AddSub=0;
Cin=0;
end
//sub
else if(opcode==4'b0011) begin
ALUOp=2'b10;
AddSub=1;
Cin=1;
end
//slt
else if(opcode==4'b1000) begin
ALUOp=2'b11;
AddSub=0;
Cin=0;
end
//andi
else if(opcode==4'b0100) begin
ALUOp=2'b00;
alu_src=1;
AddSub=0;
Cin=0;
end
//ori
else if(opcode==4'b0101) begin
ALUOp=2'b01;
alu_src=1;
AddSub=0;
Cin=0;
end
//addi
else if(opcode==4'b0110) begin
ALUOp=2'b10;
alu_src=1;
AddSub=0;
Cin=0;
end
//subi
else if(opcode==4'b0111) begin
ALUOp=2'b10;
AddSub=1;
Cin=1;
alu_src=1;
end
//slti
else if(opcode==4'b1001) begin
ALUOp=2'b11;
alu_src=1;
AddSub=0;
Cin=0;
end
//beq
else if(opcode==4'b1010) begin
ALUOp=2'b10;
AddSub=1;
Cin=1;
end
//bne
else if(opcode==4'b1011) begin
ALUOp=2'b10;
AddSub=1;
Cin=1;
end
end
else if(current_state==EXECUTE) begin
//jump
if(opcode==4'b1100) begin
jump=1;
end
//beq
else if(opcode==4'b1010) begin
if(zero_flag==1)
branch=1;
end
//bne
else if(opcode==4'b1011) begin
if(zero_flag==0)
branch=1;
end
end
else if(current_state==WRITEBACK) begin
//jump
if(opcode==4'b1100) begin
inc_PC=0;
wr_en=1;
end

//beq
else if(opcode==4'b1010) begin
wr_en=1;
if(zero_flag==1)
inc_PC=0;
else
inc_PC=1;
end
//bne
else if(opcode==4'b1011) begin
wr_en=1;
if(zero_flag==0)
inc_PC=0;
else
inc_PC=1;
end
else begin
wr_en=0; 
inc_PC=1;
end
end
end
endmodule

// --- TB ---

module tb_top();
reg clk;
reg reset;

top_lvl uut (
.clk(clk),
.reset(reset)
);

always #5 clk = ~clk;

initial begin
$monitor("TIME=%0t | PC=%d | OPCODE=%b | ALU_RES=%d | ZERO=%b | STATE=%b",
$time,
uut.DP.pc_val,
uut.op,
uut.DP.alu_res,
uut.z_flag,
uut.control.state
);
end

initial begin
$dumpfile("final_proc.vcd");
$dumpvars(0, tb_top);
clk = 0;
reset = 1;
#15;
reset = 0;

#5;
uut.DP.RF_inst.reg0.q = 4'd5;
uut.DP.RF_inst.reg1.q = 4'd3;
uut.DP.RF_inst.reg2.q = 4'd0;
uut.DP.RF_inst.reg3.q = 4'd0;
#300;
$finish;
end
endmodule

DATA_PATH_toplvl/final_proc.vcd
$date
	Sun May 03 23:36:02 2026
$end
$version
	Icarus Verilog
$end
$timescale
	1s
$end
$scope module tb_top $end
$var reg 1 ! clk $end
$var reg 1 " reset $end
$scope module uut $end
$var wire 1 ! clk $end
$var wire 1 " reset $end
$var wire 1 # z_flag $end
$var wire 1 $ w_en $end
$var wire 2 % st [1:0] $end
$var wire 4 & op [3:0] $end
$var wire 1 ' jmp $end
$var wire 1 ( i_pc $end
$var wire 1 ) br $end
$var wire 1 * a_src $end
$var wire 1 + Cin $end
$var wire 1 , AddSub $end
$var wire 2 - ALUOp [1:0] $end
$scope module DP $end
$var wire 4 . alu_B_in [3:0] $end
$var wire 1 ! clk $end
$var wire 1 " clr $end
$var wire 1 # zero_flag $end
$var wire 1 $ wr_en $end
$var wire 2 / rt [1:0] $end
$var wire 2 0 rs [1:0] $end
$var wire 2 1 rd [1:0] $end
$var wire 4 2 pc_val [3:0] $end
$var wire 1 3 ovf_flag $end
$var wire 4 4 opcode [3:0] $end
$var wire 1 ' jump $end
$var wire 16 5 inst [15:0] $end
$var wire 1 ( inc_PC $end
$var wire 4 6 d2 [3:0] $end
$var wire 4 7 d1 [3:0] $end
$var wire 1 8 caary_flag $end
$var wire 1 ) branch $end
$var wire 1 * alu_src $end
$var wire 4 9 alu_res [3:0] $end
$var wire 1 : ZF $end
$var wire 1 ; SF $end
$var wire 1 + Cin $end
$var wire 1 , AddSub $end
$var wire 2 < ALUOp [1:0] $end
$var reg 4 = mux_out [3:0] $end
$scope module ALU_inst $end
$var wire 4 > B [3:0] $end
$var wire 1 + Cin $end
$var wire 1 , AddSub $end
$var wire 2 ? ALUOp [1:0] $end
$var wire 4 @ A [3:0] $end
$var reg 1 ; SF $end
$var reg 1 : ZF $end
$var reg 4 A ans [3:0] $end
$var reg 1 8 caary_flag $end
$var reg 1 3 ovf_flag $end
$var reg 5 B x [4:0] $end
$upscope $end
$scope module IM_inst $end
$var wire 4 C addr [3:0] $end
$var reg 16 D instruction [15:0] $end
$upscope $end
$scope module PC_inst $end
$var wire 1 ! clk $end
$var wire 1 " clr $end
$var wire 4 E jump_addr [3:0] $end
$var wire 4 F ovf_flagfset [3:0] $end
$var wire 1 ' jump $end
$var wire 1 ( inc_PC $end
$var wire 1 ) branch $end
$var reg 4 G pc [3:0] $end
$upscope $end
$scope module RF_inst $end
$var wire 1 ! clk $end
$var wire 1 H clr $end
$var wire 4 I data_in [3:0] $end
$var wire 2 J rd1 [1:0] $end
$var wire 2 K rd2 [1:0] $end
$var wire 2 L wr [1:0] $end
$var wire 1 $ write_enable $end
$var wire 4 M r3 [3:0] $end
$var wire 4 N r2 [3:0] $end
$var wire 4 O r1 [3:0] $end
$var wire 4 P r0 [3:0] $end
$var wire 4 Q dec_out [3:0] $end
$var wire 4 R data_out2 [3:0] $end
$var wire 4 S data_out1 [3:0] $end
$scope module d1 $end
$var wire 2 T wr [1:0] $end
$var wire 1 $ write_enable $end
$var reg 4 U dec_out [3:0] $end
$upscope $end
$scope module m1 $end
$var wire 2 V sel [1:0] $end
$var wire 4 W in3 [3:0] $end
$var wire 4 X in2 [3:0] $end
$var wire 4 Y in1 [3:0] $end
$var wire 4 Z in0 [3:0] $end
$var reg 4 [ out [3:0] $end
$upscope $end
$scope module m2 $end
$var wire 2 \ sel [1:0] $end
$var wire 4 ] in3 [3:0] $end
$var wire 4 ^ in2 [3:0] $end
$var wire 4 _ in1 [3:0] $end
$var wire 4 ` in0 [3:0] $end
$var reg 4 a out [3:0] $end
$upscope $end
$scope module reg0 $end
$var wire 1 ! clk $end
$var wire 1 H clr $end
$var wire 4 b d [3:0] $end
$var wire 1 c load $end
$var reg 4 d q [3:0] $end
$upscope $end
$scope module reg1 $end
$var wire 1 ! clk $end
$var wire 1 H clr $end
$var wire 4 e d [3:0] $end
$var wire 1 f load $end
$var reg 4 g q [3:0] $end
$upscope $end
$scope module reg2 $end
$var wire 1 ! clk $end
$var wire 1 H clr $end
$var wire 4 h d [3:0] $end
$var wire 1 i load $end
$var reg 4 j q [3:0] $end
$upscope $end
$scope module reg3 $end
$var wire 1 ! clk $end
$var wire 1 H clr $end
$var wire 4 k d [3:0] $end
$var wire 1 l load $end
$var reg 4 m q [3:0] $end
$upscope $end
$upscope $end
$upscope $end
$scope module control $end
$var wire 1 ! clock $end
$var wire 4 n opcode [3:0] $end
$var wire 1 " reset $end
$var wire 1 # zero_flag $end
$var parameter 2 o DECODE $end
$var parameter 2 p EXECUTE $end
$var parameter 2 q FETCH $end
$var parameter 2 r WRITEBACK $end
$var reg 2 s ALUOp [1:0] $end
$var reg 1 , AddSub $end
$var reg 1 + Cin $end
$var reg 1 * alu_src $end
$var reg 1 ) branch $end
$var reg 2 t current_state [1:0] $end
$var reg 1 ( inc_PC $end
$var reg 1 ' jump $end
$var reg 2 u next_state [1:0] $end
$var reg 2 v state [1:0] $end
$var reg 1 $ wr_en $end
$upscope $end
$upscope $end
$upscope $end
$enddefinitions $end
$comment Show the parameter values. $end
$dumpall
b11 r
b0 q
b10 p
b1 o
$end
#0
$dumpvars
bx v
b1 u
b0 t
b0 s
b0 n
b0 m
0l
b0 k
b0 j
0i
b0 h
b0 g
0f
b0 e
b0 d
0c
b0 b
b0 a
b0 `
b0 _
b0 ^
b0 ]
b1 \
b0 [
b0 Z
b0 Y
b0 X
b0 W
b0 V
b0 U
b10 T
b0 S
b0 R
b0 Q
b0 P
b0 O
b0 N
b0 M
b10 L
b1 K
b0 J
b0 I
0H
b0 G
b1000 F
b1000 E
b11000 D
b0 C
bx B
b0 A
b0 @
b0 ?
b0 >
b0 =
b0 <
0;
1:
b0 9
08
b0 7
b0 6
b11000 5
b0 4
03
b0 2
b10 1
b0 0
b1 /
b0 .
b0 -
0,
0+
0*
0)
0(
0'
b0 &
bx %
1$
1#
1"
0!
$end
#5
b0 %
b0 v
1!
#10
0!
#15
b10 u
b1 t
1H
1!
0"
#20
b1 9
b1 A
b1 I
b1 b
b1 e
b1 h
b1 k
0#
0:
b11 .
b11 >
b11 =
b101 7
b101 @
b101 S
b101 [
b11 6
b11 R
b11 a
0!
b11 O
b11 Y
b11 _
b11 g
b101 P
b101 Z
b101 `
b101 d
#25
b11 u
b1 %
b1 v
b10 t
1!
#30
0!
#35
1f
b10 Q
b10 U
1(
0$
b0 u
b10 %
b10 v
b11 t
1!
#40
b1 .
b1 >
b1 =
b1 6
b1 R
b1 a
b1 O
b1 Y
b1 _
b1 g
0!
#45
0f
b11 L
b11 T
b0 Q
b0 U
b11 1
b1100 E
b1100 F
b1 &
b1 4
b1 n
0(
1$
b1 u
b100011100 5
b100011100 D
b11 %
b11 v
b0 t
b1 2
b1 C
b1 G
1!
#50
0!
#55
b101 9
b101 A
b101 I
b101 b
b101 e
b101 h
b101 k
b1 -
b1 <
b1 ?
b1 s
b10 u
b0 %
b0 v
b1 t
1!
#60
0!
#65
b1 9
b1 A
b1 I
b1 b
b1 e
b1 h
b1 k
b0 -
b0 <
b0 ?
b0 s
b11 u
b1 %
b1 v
b10 t
1!
#70
0!
#75
1l
b1000 Q
b1000 U
1(
0$
b0 u
b10 %
b10 v
b11 t
1!
#80
b1 M
b1 W
b1 ]
b1 m
0!
#85
0l
b10 L
b10 T
b0 Q
b0 U
b10 1
b1000 E
b1000 F
b10 &
b10 4
b10 n
0(
1$
b1 u
b1000011000 5
b1000011000 D
b11 %
b11 v
b0 t
b10 2
b10 C
b10 G
1!
#90
0!
#95
b110 9
b110 A
b110 I
b110 b
b110 e
b110 h
b110 k
b110 B
b10 -
b10 <
b10 ?
b10 s
b10 u
b0 %
b0 v
b1 t
1!
#100
0!
#105
b1 9
b1 A
b1 I
b1 b
b1 e
b1 h
b1 k
b0 -
b0 <
b0 ?
b0 s
b11 u
b1 %
b1 v
b10 t
1!
#110
0!
#115
1f
b10 Q
b10 U
1(
0$
b0 u
b10 %
b10 v
b11 t
1!
#120
0!
#125
0f
b11 L
b11 T
b0 Q
b0 U
b11 1
b1100 E
b1100 F
b11 &
b11 4
b11 n
0(
1$
b1 u
b1100011100 5
b1100011100 D
b11 %
b11 v
b0 t
b11 2
b11 C
b11 G
1!
#130
0!
#135
b100 9
b100 A
b100 I
b100 b
b100 e
b100 h
b100 k
b100 B
1+
1,
b10 -
b10 <
b10 ?
b10 s
b10 u
b0 %
b0 v
b1 t
1!
#140
0!
#145
b1 9
b1 A
b1 I
b1 b
b1 e
b1 h
b1 k
0+
0,
b0 -
b0 <
b0 ?
b0 s
b11 u
b1 %
b1 v
b10 t
1!
#150
0!
#155
1l
b1000 Q
b1000 U
1(
0$
b0 u
b10 %
b10 v
b11 t
1!
#160
0!
#165
0l
b10 L
b10 T
b0 Q
b0 U
b10 1
b1000 E
b1000 F
b1000 &
b1000 4
b1000 n
0(
1$
b1 u
b100000011000 5
b100000011000 D
b11 %
b11 v
b0 t
b100 2
b100 C
b100 G
1!
