ControlUnit/CU.v
//CU
module CU(
input clock,
input reset,
input [3:0] opcode,
input zero_flag,
output reg [1:0] ALUOp,
output reg AddSub, 
output reg Cin,  
output reg wr_en,
output reg alu_src,
output reg inc_PC,
output reg branch,
output reg jump,
output reg [1:0] state
);

reg [1:0] current_state;
reg [1:0] next_state;

parameter FETCH=2'b00;
parameter DECODE=2'b01;
parameter EXECUTE=2'b10;
parameter WRITEBACK=2'b11;

always @(*) begin
if(current_state==FETCH) next_state=DECODE;
else if(current_state==DECODE) next_state=EXECUTE;
else if(current_state==EXECUTE) next_state=WRITEBACK;
else if(current_state==WRITEBACK) next_state=FETCH;
else next_state=FETCH;
end

always @(posedge clock or posedge reset) begin
if(reset) current_state<=FETCH;
else current_state<=next_state;
state<=current_state;
end

always @(*) begin
ALUOp=2'b00; AddSub=0; Cin=0; wr_en=1; alu_src=0; inc_PC=0; branch=0; jump=0;
if(current_state==DECODE) begin
if(opcode==4'b0000) begin ALUOp=2'b00; end
else if(opcode==4'b0010) begin ALUOp=2'b10; end
else if(opcode==4'b0011) begin ALUOp=2'b10; AddSub=1; Cin=1; end
end
else if(current_state==EXECUTE) begin
if(opcode==4'b1100) jump=1;
end
else if(current_state==WRITEBACK) begin
if(opcode==4'b1100) inc_PC=0;
else begin wr_en=0; inc_PC=1; end
end
end
endmodule

module tb_cu();
reg clk, reset, zf; reg [3:0] op;
wire [1:0] alu_op, st; wire as, ci, we, src, ipc, br, jp;
CU uut (clk, reset, op, zf, alu_op, as, ci, we, src, ipc, br, jp, st);
always #5 clk = ~clk;
initial begin
    $dumpfile("cu_wave.vcd");
    $dumpvars(0, tb_cu);
    clk = 0; reset = 1; #10 reset = 0; op = 4'b0010; #50 $finish;
end
endmodule

ControlUnit/cu_wave.vcd
$date
	Sun May 03 23:24:59 2026
$end
$version
	Icarus Verilog
$end
$timescale
	1s
$end
$scope module tb_cu $end
$var wire 1 ! we $end
$var wire 2 " st [1:0] $end
$var wire 1 # src $end
$var wire 1 $ jp $end
$var wire 1 % ipc $end
$var wire 1 & ci $end
$var wire 1 ' br $end
$var wire 1 ( as $end
$var wire 2 ) alu_op [1:0] $end
$var reg 1 * clk $end
$var reg 4 + op [3:0] $end
$var reg 1 , reset $end
$var reg 1 - zf $end
$scope module uut $end
$var wire 1 * clock $end
$var wire 4 . opcode [3:0] $end
$var wire 1 , reset $end
$var wire 1 - zero_flag $end
$var parameter 2 / DECODE $end
$var parameter 2 0 EXECUTE $end
$var parameter 2 1 FETCH $end
$var parameter 2 2 WRITEBACK $end
$var reg 2 3 ALUOp [1:0] $end
$var reg 1 ( AddSub $end
$var reg 1 & Cin $end
$var reg 1 # alu_src $end
$var reg 1 ' branch $end
$var reg 2 4 current_state [1:0] $end
$var reg 1 % inc_PC $end
$var reg 1 $ jump $end
$var reg 2 5 next_state [1:0] $end
$var reg 2 6 state [1:0] $end
$var reg 1 ! wr_en $end
$upscope $end
$upscope $end
$enddefinitions $end
$comment Show the parameter values. $end
$dumpall
b11 2
b0 1
b10 0
b1 /
$end
#0
$dumpvars
bx 6
b1 5
b0 4
b0 3
bx .
x-
1,
bx +
0*
b0 )
0(
0'
0&
0%
0$
0#
bx "
1!
$end
#5
b0 "
b0 6
1*
#10
0*
b10 +
b10 .
0,
#15
b10 )
b10 3
b10 5
b1 4
1*
#20
0*
#25
b0 )
b0 3
b11 5
b1 "
b1 6
b10 4
1*
#30
0*
#35
1%
0!
b0 5
b10 "
b10 6
b11 4
1*
#40
0*
#45
0%
1!
b1 5
b11 "
b11 6
b0 4
1*
#50
0*
#55
b10 )
b10 3
b10 5
b0 "
b0 6
b1 4
1*
