Prog_Counter/PC.v
//Prog Counter
module program_counter(
input clk,
input clr,
input inc_PC,
input branch,
input jump,
input[3:0] ovf_flagfset,
input[3:0] jump_addr,
output reg[3:0] pc
);
always@(posedge clk or posedge clr) 
begin
if(clr)
pc<=4'b0000; 
else if(jump)
pc<=jump_addr;
else if(branch)
pc<=pc+1+ovf_flagfset; 
else if(inc_PC)
pc<=pc+1; 
end
endmodule

module tb_pc();
reg clk, clr, inc_PC, branch, jump;
reg [3:0] offset, jump_addr;
wire [3:0] pc;

program_counter uut (clk, clr, inc_PC, branch, jump, offset, jump_addr, pc);

always #5 clk = ~clk;
initial begin
    $dumpfile("pc_wave.vcd");
    $dumpvars(0, tb_pc);
    clk = 0; clr = 1; inc_PC = 0; branch = 0; jump = 0;
    #10 clr = 0; inc_PC = 1;
    #20 jump = 1; jump_addr = 4'hA;
    #10 jump = 0;
    #20 $finish;
end
endmodule

Prog_Counter/pc_wave.vcd
$date
	Sun May 03 23:22:00 2026
$end
$version
	Icarus Verilog
$end
$timescale
	1s
$end
$scope module tb_pc $end
$var wire 4 ! pc [3:0] $end
$var reg 1 " branch $end
$var reg 1 # clk $end
$var reg 1 $ clr $end
$var reg 1 % inc_PC $end
$var reg 1 & jump $end
$var reg 4 ' jump_addr [3:0] $end
$var reg 4 ( offset [3:0] $end
$scope module uut $end
$var wire 1 " branch $end
$var wire 1 # clk $end
$var wire 1 $ clr $end
$var wire 1 % inc_PC $end
$var wire 1 & jump $end
$var wire 4 ) jump_addr [3:0] $end
$var wire 4 * ovf_flagfset [3:0] $end
$var reg 4 + pc [3:0] $end
$upscope $end
$upscope $end
$enddefinitions $end
$comment Show the parameter values. $end
$dumpall
$end
#0
$dumpvars
b0 +
bx *
bx )
bx (
bx '
0&
0%
1$
0#
0"
b0 !
$end
#5
1#
#10
0#
1%
0$
#15
b1 !
b1 +
1#
#20
0#
#25
b10 !
b10 +
1#
#30
0#
b1010 '
b1010 )
1&
#35
b1010 !
b1010 +
1#
#40
0#
0&
#45
b1011 !
b1011 +
1#
#50
0#
#55
b1100 !
b1100 +
1#
